ysignals/__about__.py
ysignals/__init__.py
ysignals/__main__.py
ysignals/features.py
ysignals/data/__init__.py
ysignals/data/yahoo.py
ysignals-0.0.1rc1.dist-info/LICENSE
ysignals-0.0.1rc1.dist-info/METADATA
ysignals-0.0.1rc1.dist-info/WHEEL
ysignals-0.0.1rc1.dist-info/entry_points.txt
ysignals-0.0.1rc1.dist-info/top_level.txt
ysignals-0.0.1rc1.dist-info/zip-safe
ysignals-0.0.1rc1.dist-info/RECORD
